emqx_mcp_server/__init__.py
emqx_mcp_server/config.py
emqx_mcp_server/emqx_client.py
emqx_mcp_server/server.py
emqx_mcp_server/tools/__init__.py
emqx_mcp_server/tools/emqx_client_tools.py
emqx_mcp_server/tools/emqx_message_tools.py
mseep_emqx_mcp_server-0.1.4.dist-info/licenses/LICENSE
mseep_emqx_mcp_server-0.1.4.dist-info/METADATA
mseep_emqx_mcp_server-0.1.4.dist-info/WHEEL
mseep_emqx_mcp_server-0.1.4.dist-info/entry_points.txt
mseep_emqx_mcp_server-0.1.4.dist-info/top_level.txt
mseep_emqx_mcp_server-0.1.4.dist-info/RECORD
