Metadata-Version: 2.4
Name: mseep-emqx-mcp-server
Version: 0.1.4
Summary: A Model Context Protocol (MCP) server implementation that provides EMQX MQTT broker interaction.
Author-email: mseep <support@skydeck.ai>
Maintainer-email: Benniu Ji <benniuji@gmail.com>
License:                                  Apache License
Keywords: emqx,mqtt,mcp,llm
Requires-Python: >=3.10
License-File: LICENSE
Requires-Dist: httpx>=0.28.1
Requires-Dist: mcp[cli]>=1.3.0
Dynamic: license-file
